w96msgroom/__init__.py
w96msgroom/client.py
w96msgroom/constants.py
w96msgroom/prefix_bot.py
w96msgroom/user.py
w96msgroom-0.1.4.dist-info/METADATA
w96msgroom-0.1.4.dist-info/WHEEL
w96msgroom-0.1.4.dist-info/top_level.txt
w96msgroom-0.1.4.dist-info/RECORD
